lunas/__init__.py
lunas/iterator.py
lunas/dataset/__init__.py
lunas/dataset/core.py
lunas/dataset/generic.py
lunas/dataset/sampling.py
lunas/dataset/stdin.py
lunas/dataset/textline.py
Lunas-0.5.1.dist-info/LICENSE
Lunas-0.5.1.dist-info/METADATA
Lunas-0.5.1.dist-info/WHEEL
Lunas-0.5.1.dist-info/top_level.txt
Lunas-0.5.1.dist-info/RECORD
