Metadata-Version: 2.1
Name: Lunas
Version: 0.5.1
Summary: Building customisable data processing pipeline and data iterators for machine learning.
Home-page: https://github.com/pluiez/lunas
Author: Seann Zhang
Author-email: pluiefox@live.com
License: LICENSE
Platform: UNKNOWN
Classifier: Programming Language :: Python :: 3.7
Classifier: License :: OSI Approved :: MIT License
Classifier: Operating System :: OS Independent
Requires-Python: >=3.7
Requires-Dist: numpy
Requires-Dist: torch
